answerdiff/models.py
answerdiff/__init__.py
answerdiff/templates/answerdiff/base.html
answerdiff/static/css/answerdiff.css
answerdiff/static/js/answerdiff.js
django_answerdiff-0.1.0.dist-info/DESCRIPTION.rst
django_answerdiff-0.1.0.dist-info/metadata.json
django_answerdiff-0.1.0.dist-info/METADATA
django_answerdiff-0.1.0.dist-info/RECORD
django_answerdiff-0.1.0.dist-info/top_level.txt
django_answerdiff-0.1.0.dist-info/WHEEL
