Metadata-Version: 2.0
Name: django-answerdiff
Version: 0.1.0
Summary: Checking Submissions the Boss Way using Celery and DRF
Home-page: https://github.com/ParthKolekar/django-answerdiff
Author: Parth Kolekar
Author-email: parth.kolekar@students.iiit.ac.in
License: BSD
Keywords: django-answerdiff
Platform: UNKNOWN
Classifier: Development Status :: 3 - Alpha
Classifier: Framework :: Django
Classifier: Framework :: Django :: 1.9
Classifier: Intended Audience :: Developers
Classifier: License :: OSI Approved :: BSD License
Classifier: Natural Language :: English
Classifier: Programming Language :: Python :: 2
Classifier: Programming Language :: Python :: 2.7
